moleserv/__init__.py
moleserv/request.py
moleserv/response.py
moleserv/server.py
moleserv-0.1.5.dist-info/LICENSE.txt
moleserv-0.1.5.dist-info/METADATA
moleserv-0.1.5.dist-info/WHEEL
moleserv-0.1.5.dist-info/top_level.txt
moleserv-0.1.5.dist-info/RECORD
