Metadata-Version: 2.1
Name: moleserv
Version: 0.1.5
Summary: Molerat protocol server library.
Home-page: https://molerat.trinket.icu
Author: Shav Kinderlehrer
Author-email: molerat@git.trinket.icu
License: 0BSD
Project-URL: Source, https://git.trinket.icu/moleserv.git
Project-URL: Github, https://github.com/secondary-smiles/moleserv
Keywords: network server library molerat protocol
Classifier: License :: OSI Approved :: BSD License
Classifier: Programming Language :: Python :: 3 :: Only
Classifier: Programming Language :: Python :: 3.11
Classifier: Topic :: Communications
Classifier: Topic :: Communications :: File Sharing
Classifier: Topic :: Internet
Classifier: Topic :: Software Development :: Libraries
Requires-Python: >=3.11
License-File: LICENSE.txt
Requires-Dist: pyOpenSSL
